mapfile_parser/__init__.py
mapfile_parser/__main__.py
mapfile_parser/frontends/__init__.py
mapfile_parser/frontends/bss_check.py
mapfile_parser/frontends/first_diff.py
mapfile_parser/frontends/jsonify.py
mapfile_parser/frontends/objdiff_report.py
mapfile_parser/frontends/pj64_syms.py
mapfile_parser/frontends/progress.py
mapfile_parser/frontends/sym_info.py
mapfile_parser/frontends/symbol_sizes_csv.py
mapfile_parser/frontends/upload_frogress.py
mapfile_parser/internals/__init__.py
mapfile_parser/internals/objdiff_report.py
mapfile_parser/mapfile.py
mapfile_parser/mapfile_parser.cpython-314t-i386-linux-musl.so
mapfile_parser/mapfile_parser.pyi
mapfile_parser/mapfile_rs.py
mapfile_parser/progress_stats.py
mapfile_parser/progress_stats_rs.py
mapfile_parser/utils.py
mapfile_parser-2.12.1.dist-info/METADATA
mapfile_parser-2.12.1.dist-info/WHEEL
mapfile_parser-2.12.1.dist-info/entry_points.txt
mapfile_parser-2.12.1.dist-info/licenses/LICENSE
mapfile_parser.libs/libgcc_s-f5fcfe20.so.1
mapfile_parser-2.12.1.dist-info/RECORD
