Metadata-Version: 2.4
Name: mapfile_parser
Version: 2.12.1
Classifier: Programming Language :: Rust
Classifier: Programming Language :: Python :: Implementation :: CPython
Classifier: Programming Language :: Python :: Implementation :: PyPy
Requires-Dist: requests
Requires-Dist: decomp-settings==0.0.10
License-File: LICENSE
Summary: Map file parser library focusing decompilation projects
Requires-Python: >=3.8
Project-URL: Bug Tracker, https://github.com/Decompollaborate/mapfile_parser/issues
Project-URL: Homepage, https://github.com/Decompollaborate/mapfile_parser
